threedtool/__init__.py
threedtool/annotations.py
threedtool/core/__init__.py
threedtool/core/basefigure.py
threedtool/core/cuboid.py
threedtool/core/line.py
threedtool/core/origin.py
threedtool/core/plane.py
threedtool/core/prism.py
threedtool/core/prismoid.py
threedtool/core/sphere.py
threedtool/display/__init__.py
threedtool/display/dspl.py
threedtool/fmath/__init__.py
threedtool/fmath/dispatch.py
threedtool/fmath/fmath.py
threedtool/fmath/handlers.py
threedtool/fmath/intersections.py
threedtool-0.0.8.dist-info/licenses/LICENSE
threedtool-0.0.8.dist-info/METADATA
threedtool-0.0.8.dist-info/WHEEL
threedtool-0.0.8.dist-info/top_level.txt
threedtool-0.0.8.dist-info/RECORD
